trenchview/__init__.py
trenchview/cli.py
trenchview/formatting.py
trenchview/parsing.py
trenchview/scraping.py
trenchview/telethon.py
trenchview/types.py
trenchview-0.1.0.dist-info/LICENSE
trenchview-0.1.0.dist-info/METADATA
trenchview-0.1.0.dist-info/WHEEL
trenchview-0.1.0.dist-info/entry_points.txt
trenchview-0.1.0.dist-info/RECORD
